LICENSE
MANIFEST.in
README.rst
setup.py
battlenet/__init__.py
battlenet/connection.py
battlenet/constants.py
battlenet/enums.py
battlenet/exceptions.py
battlenet/things.py
battlenet/utils.py
battlenet.egg-info/PKG-INFO
battlenet.egg-info/SOURCES.txt
battlenet.egg-info/dependency_links.txt
battlenet.egg-info/top_level.txt
tests/__init__.py
tests/test_character.py
tests/test_eventlet.py
tests/test_exceptions.py
tests/test_guild.py
tests/test_realm.py
tests/test_regions.py