Metadata-Version: 1.0
Name: battlenet
Version: 0.2.6
Summary: Python Library for Blizzard's Community Platform API
Home-page: https://github.com/vishnevskiy/battlenet
Author: Stanislav Vishnevskiy
Author-email: vishnevskiy@gmail.com
License: MIT
Platform: any
Classifier: Development Status :: 4 - Beta
Classifier: Intended Audience :: Developers
Classifier: License :: OSI Approved :: MIT License
Classifier: Operating System :: OS Independent
Classifier: Programming Language :: Python
Classifier: Topic :: Software Development :: Libraries :: Python Modules
